maxwell/__init__.py
maxwell/protocol/__init__.py
maxwell/protocol/maxwell_protocol.py
maxwell/protocol/maxwell_protocol_pb2.py
maxwell_protocol-0.9.2.dist-info/METADATA
maxwell_protocol-0.9.2.dist-info/WHEEL
maxwell_protocol-0.9.2.dist-info/licenses/LICENSE
maxwell_protocol-0.9.2.dist-info/RECORD
