Metadata-Version: 2.3
Name: maxwell-protocol
Version: 0.9.2
Summary: The maxwell protocol implementation for python.
Project-URL: changelog, https://github.com/maxwell-dev/maxwell-protocol-python/CHANGELOG.md
Project-URL: repository, https://github.com/maxwell-dev/maxwell-protocol-python
Author-email: Xu Chaoqian <chaoranxu@gmail.com>
License:                                  Apache License
License-File: LICENSE
Classifier: License :: OSI Approved :: MIT License
Classifier: Operating System :: OS Independent
Classifier: Programming Language :: Python :: 3
Requires-Python: >=3.7
Requires-Dist: protobuf==5.28.0
Provides-Extra: test
Requires-Dist: pytest-cov>=5.0.0; extra == 'test'
Requires-Dist: pytest>=8.3.2; extra == 'test'
